bia_bubbles/__init__.py
bia_bubbles/data/__init__.py
bia_bubbles/data/binary_blobs.png
bia_bubbles/data/binary_noise.png
bia_bubbles/data/blob.png
bia_bubbles/data/blobs.tif
bia_bubbles/data/crop.png
bia_bubbles/data/crop_binary.png
bia_bubbles/data/human_mitosis_small.png
bia_bubbles/data/human_mitosis_small_wo_bg.png
bia_bubbles/data/level0.yaml
bia_bubbles/data/level1.yaml
bia_bubbles/data/level10.yaml
bia_bubbles/data/level11.yaml
bia_bubbles/data/level12.yaml
bia_bubbles/data/level2.yaml
bia_bubbles/data/level3.yaml
bia_bubbles/data/level4.yaml
bia_bubbles/data/level5.yaml
bia_bubbles/data/level6.yaml
bia_bubbles/data/level7.yaml
bia_bubbles/data/level8.yaml
bia_bubbles/data/level9.yaml
bia_bubbles/data/maize_clsm.tif
bia_bubbles/data/membranes.png
bia_bubbles/data/noise.png
bia_bubbles/data/uneven_illumination.png
bia_bubbles-0.1.2.dist-info/licenses/LICENSE
bia_bubbles-0.1.2.dist-info/METADATA
bia_bubbles-0.1.2.dist-info/WHEEL
bia_bubbles-0.1.2.dist-info/entry_points.txt
bia_bubbles-0.1.2.dist-info/top_level.txt
bia_bubbles-0.1.2.dist-info/RECORD
