Metadata-Version: 2.4
Name: bia-bubbles
Version: 0.1.2
Summary: A game to practice bio-image analysis skills.
Home-page: https://github.com/haesleinhuepf/bia-bubbles
Author: Robert Haase
Author-email: robert.haase@uni-leipzig.de
License: BSD-3-Clause
Project-URL: Bug Tracker, https://github.com/haesleinhuepf/bia-bubbles/issues
Project-URL: Documentation, https://github.com/haesleinhuepf/bia-bubbles#README.md
Project-URL: Source Code, https://github.com/haesleinhuepf/bia-bubbles
Project-URL: User Support, https://github.com/haesleinhuepf/bia-bubbles/issues
Classifier: Development Status :: 2 - Pre-Alpha
Classifier: Intended Audience :: Developers
Classifier: License :: OSI Approved :: BSD License
Classifier: Operating System :: OS Independent
Classifier: Programming Language :: Python
Classifier: Programming Language :: Python :: 3
Classifier: Programming Language :: Python :: 3.9
Classifier: Programming Language :: Python :: 3.10
Classifier: Programming Language :: Python :: 3.11
Requires-Python: >=3.9
License-File: LICENSE
Requires-Dist: pygame
Requires-Dist: numpy
Requires-Dist: matplotlib
Requires-Dist: pyclesperanto
Requires-Dist: scikit-image
Requires-Dist: scipy
Provides-Extra: testing
Requires-Dist: tox; extra == "testing"
Requires-Dist: pytest; extra == "testing"
Requires-Dist: pytest-cov; extra == "testing"
Dynamic: license-file
